cotdantic/__init__.py
cotdantic/contacts.py
cotdantic/converters.py
cotdantic/cot_types.py
cotdantic/cotdantic.py
cotdantic/datapack.py
cotdantic/models.py
cotdantic/multicast.py
cotdantic/templates.py
cotdantic/utilities.py
cotdantic/windows.py
cotdantic-2.1.5.dist-info/LICENSE
cotdantic-2.1.5.dist-info/METADATA
cotdantic-2.1.5.dist-info/WHEEL
cotdantic-2.1.5.dist-info/entry_points.txt
cotdantic-2.1.5.dist-info/top_level.txt
cotdantic-2.1.5.dist-info/RECORD
