Metadata-Version: 2.2
Name: cotdantic
Version: 2.1.5
Summary: Pythonic coursor-on-target xml/protobuf generation using pydantic
Author: Raub Camaioni
Maintainer: Raub Camaioni
License: MIT License
Project-URL: Homepage, https://github.com/RaubCamaioni/cotdantic
Keywords: cot,coursor,target
Requires-Python: >=3.8
License-File: LICENSE
Requires-Dist: takproto>=3.0.0
Requires-Dist: pydantic_xml>=2.0.0
Requires-Dist: lxml>=5.3.0
Requires-Dist: toml
Requires-Dist: windows-curses; sys_platform == "win32"
Provides-Extra: testing
Requires-Dist: pytest>=6.2.4; extra == "testing"
Provides-Extra: dev
Requires-Dist: pytest>=6.2.4; extra == "dev"
Requires-Dist: nox[uv]; extra == "dev"
Requires-Dist: pre-commit; extra == "dev"
